LICENSE
pydantic_spark/__init__.py
pydantic_spark/__main__.py
pydantic_spark/base.py
pydantic_spark/spark_to_pydantic.py
pydantic_spark-1.0.1.dist-info/LICENSE
pydantic_spark-1.0.1.dist-info/METADATA
pydantic_spark-1.0.1.dist-info/WHEEL
pydantic_spark-1.0.1.dist-info/entry_points.txt
pydantic_spark-1.0.1.dist-info/RECORD
