Metadata-Version: 2.1
Name: pydantic-spark
Version: 1.0.1
Summary: Converting pydantic classes to spark schemas
Home-page: https://github.com/godatadriven/pydantic-spark
License: MIT
Keywords: pydantic,spark
Author: Peter van 't Hof'
Author-email: peter.vanthof@godatadriven.com
Requires-Python: >=3.8,<4.0
Classifier: License :: OSI Approved :: MIT License
Classifier: Programming Language :: Python :: 3
Classifier: Programming Language :: Python :: 3.8
Classifier: Programming Language :: Python :: 3.9
Classifier: Programming Language :: Python :: 3.10
Classifier: Programming Language :: Python :: 3.11
Classifier: Programming Language :: Python :: 3.12
Provides-Extra: spark
Requires-Dist: pydantic (>=2.5.2,<3.0.0)
Requires-Dist: pyspark (>=3.1.2,<3.3.0) ; extra == "spark"
Project-URL: Repository, https://github.com/godatadriven/pydantic-spark
